slimp/__init__.py
slimp/_slimp.cpython-313-x86_64-linux-gnu.so
slimp/compile.py
slimp/libslimp.so
slimp/libslimp.so.1.1.1
slimp/misc.py
slimp/model.py
slimp/plots.py
slimp/samples.py
slimp/stats.py
slimp/multilevel/__init__.py
slimp/multilevel/model_data.py
slimp/multilevel/predictor_mapper.py
slimp/multivariate/__init__.py
slimp/multivariate/model_data.py
slimp/multivariate/predictor_mapper.py
slimp/univariate/__init__.py
slimp/univariate/model_data.py
slimp/univariate/predictor_mapper.py
slimp-1.1.1.dist-info/licenses/LICENSE
slimp-1.1.1.dist-info/METADATA
slimp-1.1.1.dist-info/WHEEL
slimp-1.1.1.dist-info/top_level.txt
slimp-1.1.1.dist-info/RECORD
